{
    "1271500729537794229": {
        "score": 2,
        "name": "Niko",
        "chances": {
            "silly-bot_replies": 2,
            "stupid_says": 2,
            "WAAAAT_replies": 2,
            "mocking": 2,
            "random_replies": 1
        }
    },
    "483868190498357248": {
        "score": 0,
        "name": "Deadguana",
        "chances": {
            "stupid_says": 1,
            "silly-bot_replies": 1,
            "random_replies": 1,
            "mocking": 1
        }
    },
    "853629533855809596": {
        "score": 0,
        "name": "SOFI",
        "chances": {
            "mocking": 2
        }
    },
    "279880443200012288": {
        "score": 2,
        "name": "seam",
        "chances": {
            "stupid_says": 2,
            "random_replies": 2,
            "mocking": 1
        }
    },
    "1474033945292177541": {
        "score": 0,
        "name": "poopid BETA",
        "chances": {
            "stupid_says": 1,
            "random_replies": 1
        }
    }
}